Workbook

Sheet README
A1: WorkInSync Seat-Planning Model
A2: Case-model template. Blue cells are editable inputs; black cells contain live formulas.
A4: Purpose | B4: Model min-max seat demand and a Facilities KPI scorecard for the case study.
A6: How to use | B6: 1. Update blue cells in Inputs. 2. Review scenario validation. 3. Review per-office sizing, sensitivity, and KPI template.
A8: Important | B8: All values are modeled estimates. Scenario B/C profiles and KPI samples are assumptions or SYNTHETIC / ILLUSTRATIVE.
A10: Color legend | B10: Blue = editable input; Black = formula/output; Green = validated/illustrative output.
A12: Model logic | B12: Seats = MIN(headcount, ROUNDUP(peak attendance × (1 + buffer), 0)). Offices cannot pool seats across countries.
A14: Recommendation logic | B14: Use managed attendance plus an additional contingency only after the pilot; review with real check-in data after 8 weeks.

Sheet Inputs
A1: Inputs
A2: Editable parameters. Illustrative defaults are assumptions, not customer facts.
A4: Global input | B4: Value | C4: Status / note | E4: Policy adherence | F4: Value
A5: Total headcount | B5: 2000 | C5: Given in case | E5: 80% | F5: 0.8
A6: In-office days per person / week | B6: 3 | C6: Given in case | E6: 90% | F6: 0.9
A7: Default working days / week | B7: 5 | C7: Assumption; per-office override allowed | E7: 100% | F7: 1
A8: Planning buffer | B8: 0.05 | C8: Assumption
A9: Confidence level | B9: 0.95 | C9: Assumption
A10: z score | B10: 1.645 | C10: Assumption
A11: One (formula constant) | B11: 1 | C11: Technical input; do not change
A12: Rounding digits | B12: 0 | C12: Technical input; do not change
A13: Attendance probability p | B13: =B6/B7 -> 0.6 | C13: Formula: days / working days
A14: High-peak buffer | B14: 0.1 | C14: Sensitivity assumption
A16: Scenario profiles (attendance % of headcount) | B16: Mon | C16: Tue | D16: Wed | E16: Thu | F16: Fri | G16: Profile note
A17: A. Perfectly balanced | B17: 0.6 | C17: 0.6 | D17: 0.6 | E17: 0.6 | F17: 0.6 | G17: Policy-assigned days
A18: B. Managed | B18: 0.5 | C18: 0.65 | D18: 0.65 | E18: 0.65 | F18: 0.55 | G18: MODELING ASSUMPTION: team anchors / soft cap
A19: C. Unmanaged | B19: 0.45 | C19: 0.7 | D19: 0.75 | E19: 0.7 | F19: 0.4 | G19: MODELING ASSUMPTION: free choice / Tue-Thu skew
A20: D. Worst case | B20: 1 | C20: 1 | D20: 1 | E20: 0 | F20: 0 | G20: All choose the same three days
A23: Illustrative per-office inputs | B23: Headcount | C23: Working days | D23: Planning peak | E23: Buffer | F23: Country
A24: Office 1 | B24: 1000 | C24: 5 | D24: 0.65 | E24: 0.05 | F24: UNKNOWN
A25: Office 2 | B25: 600 | C25: 5 | D25: 0.65 | E25: 0.05 | F25: UNKNOWN
A26: Office 3 | B26: 400 | C26: 5 | D26: 0.65 | E26: 0.05 | F26: UNKNOWN
A29: SYNTHETIC / ILLUSTRATIVE KPI sample inputs | B29: Sample | C29: Illustrative target
A30: Peak-day utilization | B30: 0.86 | C30: 80–90%; calibrate after 4–8 week baseline
A31: Weekday utilization skew | B31: 0.18 | C31: Narrowing; calibrate after baseline
A32: Cost / employee-day | B32: 42 | C32: Trending down; calibrate after baseline
A33: Seat denial rate | B33: 0.015 | C33: <2%; calibrate after baseline
A34: No-show rate | B34: 0.12 | C34: <10–15%; calibrate after baseline
A35: Workplace CSAT | B35: 4.2 | C35: ≥4/5; calibrate after baseline
A36: Team co-presence | B36: 0.78 | C36: Improving; calibrate after baseline
A37: Ticket SLA adherence | B37: 0.96 | C37: ≥95%; calibrate after baseline
A38: Repeat-issue rate | B38: 0.08 | C38: Down; calibrate after baseline
A39: Open critical incidents | B39: 0 | C39: Zero critical open; calibrate after baseline
A40: Energy / occupied seat-day | B40: 5.6 | C40: Down vs baseline
A41: Budget variance | B41: 0.03 | C41: Within ±5%; calibrate after baseline

Sheet Scenarios
A1: Scenarios
A2: All outputs use Inputs sheet references. Scenario B and C profiles are modeling assumptions.
A5: Scenario | B5: Mon load | C5: Tue load | D5: Wed load | E5: Thu load | F5: Fri load | G5: Profile sum | H5: Validation | I5: Peak load | J5: Seats with buffer
A6: =Inputs!$A$17 -> A. Perfectly balanced | B6: =Inputs!$B$5*Inputs!$B$17 -> 1200 | C6: =Inputs!$B$5*Inputs!$C$17 -> 1200 | D6: =Inputs!$B$5*Inputs!$D$17 -> 1200 | E6: =Inputs!$B$5*Inputs!$E$17 -> 1200 | F6: =Inputs!$B$5*Inputs!$F$17 -> 1200 | G6: =SUM(Inputs!$B$17:Inputs!$F$17) -> 3 | H6: =IF(G6=Inputs!$B$6,"OK","CHECK") -> OK | I6: =MAX(B6:F6) -> 1200 | J6: =MIN(Inputs!$B$5,ROUNDUP(I6*(Inputs!$B$11+Inputs!$B$8),Inputs!$B$12)) -> 1260
A7: =Inputs!$A$18 -> B. Managed | B7: =Inputs!$B$5*Inputs!$B$18 -> 1000 | C7: =Inputs!$B$5*Inputs!$C$18 -> 1300 | D7: =Inputs!$B$5*Inputs!$D$18 -> 1300 | E7: =Inputs!$B$5*Inputs!$E$18 -> 1300 | F7: =Inputs!$B$5*Inputs!$F$18 -> 1100 | G7: =SUM(Inputs!$B$18:Inputs!$F$18) -> 3 | H7: =IF(G7=Inputs!$B$6,"OK","CHECK") -> OK | I7: =MAX(B7:F7) -> 1300 | J7: =MIN(Inputs!$B$5,ROUNDUP(I7*(Inputs!$B$11+Inputs!$B$8),Inputs!$B$12)) -> 1365
A8: =Inputs!$A$19 -> C. Unmanaged | B8: =Inputs!$B$5*Inputs!$B$19 -> 900 | C8: =Inputs!$B$5*Inputs!$C$19 -> 1400 | D8: =Inputs!$B$5*Inputs!$D$19 -> 1500 | E8: =Inputs!$B$5*Inputs!$E$19 -> 1400 | F8: =Inputs!$B$5*Inputs!$F$19 -> 800 | G8: =SUM(Inputs!$B$19:Inputs!$F$19) -> 3 | H8: =IF(G8=Inputs!$B$6,"OK","CHECK") -> OK | I8: =MAX(B8:F8) -> 1500 | J8: =MIN(Inputs!$B$5,ROUNDUP(I8*(Inputs!$B$11+Inputs!$B$8),Inputs!$B$12)) -> 1575
A9: =Inputs!$A$20 -> D. Worst case | B9: =Inputs!$B$5*Inputs!$B$20 -> 2000 | C9: =Inputs!$B$5*Inputs!$C$20 -> 2000 | D9: =Inputs!$B$5*Inputs!$D$20 -> 2000 | E9: =Inputs!$B$5*Inputs!$E$20 -> 0 | F9: =Inputs!$B$5*Inputs!$F$20 -> 0 | G9: =SUM(Inputs!$B$20:Inputs!$F$20) -> 3 | H9: =IF(G9=Inputs!$B$6,"OK","CHECK") -> OK | I9: =MAX(B9:F9) -> 2000 | J9: =MIN(Inputs!$B$5,ROUNDUP(I9*(Inputs!$B$11+Inputs!$B$8),Inputs!$B$12)) -> 2000
A12: Interpretation | B12: Average daily load is a hard floor. Peak-day behavior—not average attendance—determines the desk count.

Sheet Per_Office
A1: Per_Office
A2: Illustrative split only. Seats are sized separately because capacity cannot be pooled across countries.
A5: Office | B5: Country | C5: Headcount | D5: Working days | E5: p = days / week | F5: Planning peak | G5: Buffer | H5: Seats required
A6: =Inputs!$A$24 -> Office 1 | B6: =Inputs!$F$24 -> UNKNOWN | C6: =Inputs!$B$24 -> 1000 | D6: =Inputs!$C$24 -> 5 | E6: =Inputs!$B$6/D6 -> 0.6 | F6: =Inputs!$D$24 -> 0.65 | G6: =Inputs!$E$24 -> 0.05 | H6: =MIN(C6,ROUNDUP(C6*F6*(Inputs!$B$11+G6),Inputs!$B$12)) -> 683
A7: =Inputs!$A$25 -> Office 2 | B7: =Inputs!$F$25 -> UNKNOWN | C7: =Inputs!$B$25 -> 600 | D7: =Inputs!$C$25 -> 5 | E7: =Inputs!$B$6/D7 -> 0.6 | F7: =Inputs!$D$25 -> 0.65 | G7: =Inputs!$E$25 -> 0.05 | H7: =MIN(C7,ROUNDUP(C7*F7*(Inputs!$B$11+G7),Inputs!$B$12)) -> 410
A8: =Inputs!$A$26 -> Office 3 | B8: =Inputs!$F$26 -> UNKNOWN | C8: =Inputs!$B$26 -> 400 | D8: =Inputs!$C$26 -> 5 | E8: =Inputs!$B$6/D8 -> 0.6 | F8: =Inputs!$D$26 -> 0.65 | G8: =Inputs!$E$26 -> 0.05 | H8: =MIN(C8,ROUNDUP(C8*F8*(Inputs!$B$11+G8),Inputs!$B$12)) -> 273
A10: Total | H10: =SUM(H6:H8) -> 1366
A12: Worked illustration | B12: At 65% planning peak and 5% buffer: 683 / 410 / 273 = 1,366 seats.

Sheet Stats_Check
A1: Stats_Check
A2: Independent-randomness check. The case conclusion is that correlated behavior, not randomness, creates the large min-max spread.
A5: Population n | B5: Mean n×p | C5: Std. dev. | D5: 95% peak | E5: Margin vs mean
A6: =Inputs!$B$5 -> 2000 | B6: =A6*Inputs!$B$13 -> 1200 | C6: =SQRT(A6*Inputs!$B$13*(Inputs!$B$11-Inputs!$B$13)) -> 21.909 | D6: =B6+Inputs!$B$10*C6 -> 1236.04 | E6: =(D6-B6)/B6 -> 0.03
A7: =Inputs!$B$24 -> 1000 | B7: =A7*Inputs!$B$13 -> 600 | C7: =SQRT(A7*Inputs!$B$13*(Inputs!$B$11-Inputs!$B$13)) -> 15.492 | D7: =B7+Inputs!$B$10*C7 -> 625.48 | E7: =(D7-B7)/B7 -> 0.0425
A8: =Inputs!$B$26 -> 400 | B8: =A8*Inputs!$B$13 -> 240 | C8: =SQRT(A8*Inputs!$B$13*(Inputs!$B$11-Inputs!$B$13)) -> 9.798 | D8: =B8+Inputs!$B$10*C8 -> 256.12 | E8: =(D8-B8)/B8 -> 0.0672
A11: Conclusion | B11: Random variation adds ~3% for 2,000 people; policy and booking must manage correlated weekday peaks. Smaller offices need a larger relative buffer.

Sheet Sensitivity
A1: Sensitivity
A2: Computed scenarios show the effect of working days, peak attendance, buffer, and policy adherence.
A5: Case | B5: Working days | C5: Peak attendance | D5: Buffer | E5: Policy adherence | F5: Required seats
A6: Balanced / 5-day | B6: =Inputs!$B$7 -> 5 | C6: =Inputs!$B$13 -> 0.6 | D6: =Inputs!$B$8 -> 0.05 | E6: =Inputs!$F$7 -> 1 | F6: =MIN(Inputs!$B$5,ROUNDUP(Inputs!$B$5*C6*(Inputs!$B$11+D6),Inputs!$B$12)) -> 1260
A7: Managed / 5-day | B7: =Inputs!$B$7 -> 5 | C7: =MAX(Inputs!$B$18:Inputs!$F$18) -> 0.65 | D7: =Inputs!$B$8 -> 0.05 | E7: =Inputs!$F$7 -> 1 | F7: =MIN(Inputs!$B$5,ROUNDUP(Inputs!$B$5*C7*(Inputs!$B$11+D7),Inputs!$B$12)) -> 1365
A8: 6-day average | B8: =Inputs!$B$7+Inputs!$B$11 -> 6 | C8: =Inputs!$B$6/B8 -> 0.5 | D8: =Inputs!$B$8 -> 0.05 | E8: =Inputs!$F$7 -> 1 | F8: =MIN(Inputs!$B$5,ROUNDUP(Inputs!$B$5*C8*(Inputs!$B$11+D8),Inputs!$B$12)) -> 1050
A9: High peak + buffer | B9: =Inputs!$B$7 -> 5 | C9: =MAX(Inputs!$B$19:Inputs!$F$19) -> 0.75 | D9: =Inputs!$B$14 -> 0.1 | E9: =Inputs!$F$7 -> 1 | F9: =MIN(Inputs!$B$5,ROUNDUP(Inputs!$B$5*C9*(Inputs!$B$11+D9),Inputs!$B$12)) -> 1650
A10: Managed / 80% adherence | B10: =Inputs!$B$7 -> 5 | C10: =Inputs!$B$11-(Inputs!$B$11-MAX(Inputs!$B$18:Inputs!$F$18))*E10 -> 0.72 | D10: =Inputs!$B$8 -> 0.05 | E10: =Inputs!$F$5 -> 0.8 | F10: =MIN(Inputs!$B$5,ROUNDUP(Inputs!$B$5*C10*(Inputs!$B$11+D10),Inputs!$B$12)) -> 1512
A11: Managed / 90% adherence | B11: =Inputs!$B$7 -> 5 | C11: =Inputs!$B$11-(Inputs!$B$11-MAX(Inputs!$B$18:Inputs!$F$18))*E11 -> 0.685 | D11: =Inputs!$B$8 -> 0.05 | E11: =Inputs!$F$6 -> 0.9 | F11: =MIN(Inputs!$B$5,ROUNDUP(Inputs!$B$5*C11*(Inputs!$B$11+D11),Inputs!$B$12)) -> 1439
A12: Managed / 100% adherence | B12: =Inputs!$B$7 -> 5 | C12: =Inputs!$B$11-(Inputs!$B$11-MAX(Inputs!$B$18:Inputs!$F$18))*E12 -> 0.65 | D12: =Inputs!$B$8 -> 0.05 | E12: =Inputs!$F$7 -> 1 | F12: =MIN(Inputs!$B$5,ROUNDUP(Inputs!$B$5*C12*(Inputs!$B$11+D12),Inputs!$B$12)) -> 1365
A15: Adherence method | B15: For 80–100% adherence rows, conservative peak = 1 − (1 − managed peak) × adherence. It is a modeling assumption, not a forecast.

Sheet KPI_Scorecard
A1: KPI_Scorecard
A2: SYNTHETIC / ILLUSTRATIVE sample data. Every target must be calibrated after a 4–8 week baseline.
A5: Group | B5: KPI | C5: Definition / formula | D5: Data source needed | E5: Frequency | F5: Owner | G5: Illustrative target | H5: Synthetic sample
A6: Space efficiency | B6: Peak-day utilization | C6: Peak occupied seats / total seats | D6: Check-in or badge data + seats | E6: Weekly | F6: Facilities | G6: =Inputs!$C$30 -> 80–90%; calibrate after baseline | H6: =Inputs!$B$30 -> 0.86
A7: Space efficiency | B7: Weekday utilization skew | C7: Max weekday utilization − min weekday utilization | D7: Check-in or badge data | E7: Weekly | F7: Facilities + policy | G7: =Inputs!$C$31 -> Narrowing; calibrate after baseline | H7: =Inputs!$B$31 -> 0.18
A8: Space efficiency | B8: Cost / employee-day | C8: Occupancy cost / employee-days present | D8: Occupancy cost + presence data | E8: Monthly | F8: Facilities + Finance | G8: =Inputs!$C$32 -> Trending down; calibrate after baseline | H8: =Inputs!$B$32 -> 42
A9: Booking quality | B9: Seat denial rate | C9: Failed booking attempts / attempts | D9: Booking records | E9: Weekly | F9: Facilities | G9: =Inputs!$C$33 -> <2%; calibrate after baseline | H9: =Inputs!$B$33 -> 0.015
A10: Booking quality | B10: No-show rate | C10: Booked but not checked in / booked | D10: Booking + check-in records | E10: Weekly | F10: Facilities | G10: =Inputs!$C$34 -> <10–15%; calibrate after baseline | H10: =Inputs!$B$34 -> 0.12
A11: Employee experience | B11: Workplace CSAT | C11: Pulse survey score | D11: Survey | E11: Monthly / quarterly | F11: Shared with leadership | G11: =Inputs!$C$35 -> ≥4/5; calibrate after baseline | H11: =Inputs!$B$35 -> 4.2
A12: Employee experience | B12: Team co-presence | C12: Team anchor days meeting participation threshold / anchor days | D12: Badge/check-in + team roster | E12: Monthly | F12: Shared with leadership | G12: =Inputs!$C$36 -> Improving; calibrate after baseline | H12: =Inputs!$B$36 -> 0.78
A13: Service operations | B13: Ticket SLA adherence | C13: Tickets resolved within SLA / total | D13: Ticket system | E13: Weekly | F13: Facilities | G13: =Inputs!$C$37 -> ≥95%; calibrate after baseline | H13: =Inputs!$B$37 -> 0.96
A14: Service operations | B14: Repeat-issue rate | C14: Repeat tickets / total tickets | D14: Ticket system | E14: Monthly | F14: Facilities | G14: =Inputs!$C$38 -> Down; calibrate after baseline | H14: =Inputs!$B$38 -> 0.08
A15: Safety & compliance | B15: Open critical incidents | C15: Count of critical incidents or audit findings open | D15: Incident/audit records | E15: Weekly | F15: Facilities | G15: =Inputs!$C$39 -> Zero critical open; calibrate after baseline | H15: =Inputs!$B$39 -> 0
A16: Sustainability | B16: Energy / occupied seat-day | C16: kWh / occupied seat-days | D16: Utility meters + presence data | E16: Monthly | F16: Facilities | G16: =Inputs!$C$40 -> Down vs baseline | H16: =Inputs!$B$40 -> 5.6
A17: Financial | B17: Budget variance | C17: (Actual − plan) / plan; track space cost avoided | D17: Finance + occupancy data | E17: Monthly | F17: Facilities + Finance | G17: =Inputs!$C$41 -> Within ±5%; calibrate after baseline | H17: =Inputs!$B$41 -> 0.03
A20: Balanced reading | B20: Read utilization alongside denial rate and CSAT; booking/no-shows lead, while CSAT and cost lag. Report by office and country once data exists.

Sheet Charts
A1: Charts
A2: Chart source data and native Excel charts. All data is linked to formula outputs.
A5: Scenario | B5: Seats | D5: Scenario | E5: Peak load | G5: Sensitivity case | H5: Seats
A6: A. Balanced | B6: =Scenarios!$J$6 -> 1260 | D6: A. Balanced | E6: =Scenarios!$I$6 -> 1200
A7: B. Managed | B7: =Scenarios!$J$7 -> 1365 | D7: B. Managed | E7: =Scenarios!$I$7 -> 1300
A8: C. Unmanaged | B8: =Scenarios!$J$8 -> 1575 | D8: C. Unmanaged | E8: =Scenarios!$I$8 -> 1500
A9: D. Worst case | B9: =Scenarios!$J$9 -> 2000 | D9: D. Worst case | E9: =Scenarios!$I$9 -> 2000
G6: =Sensitivity!$A$6 -> Balanced / 5-day | H6: =Sensitivity!$F$6 -> 1260
G7: =Sensitivity!$A$7 -> Managed / 5-day | H7: =Sensitivity!$F$7 -> 1365
G8: =Sensitivity!$A$8 -> 6-day average | H8: =Sensitivity!$F$8 -> 1050
G9: =Sensitivity!$A$9 -> High peak + buffer | H9: =Sensitivity!$F$9 -> 1650
G10: =Sensitivity!$A$10 -> Managed / 80% adherence | H10: =Sensitivity!$F$10 -> 1512
G11: =Sensitivity!$A$11 -> Managed / 90% adherence | H11: =Sensitivity!$F$11 -> 1439
G12: =Sensitivity!$A$12 -> Managed / 100% adherence | H12: =Sensitivity!$F$12 -> 1365
